mle_training_housing/__init__.py
mle_training_housing/config.py
mle_training_housing/ingest_data.py
mle_training_housing/score.py
mle_training_housing/train.py
mle_training_housing/utils.py
mle_training_housing-0.2.9.dist-info/LICENSE.txt
mle_training_housing-0.2.9.dist-info/METADATA
mle_training_housing-0.2.9.dist-info/WHEEL
mle_training_housing-0.2.9.dist-info/entry_points.txt
mle_training_housing-0.2.9.dist-info/top_level.txt
mle_training_housing-0.2.9.dist-info/RECORD
