Metadata-Version: 2.1
Name: mle-training-housing
Version: 0.2.9
Summary: Training on python packaging and testing
Home-page: http://github.com/vinithsrinivas/mle-training
Author: Vinith
Author-email: vinith.jegathees@tigeranalytics.com
License: TA
Keywords: MLE Training - Housing
Platform: UNKNOWN
Classifier: Development Status :: 3 - Alpha
Requires-Dist: pandas
Requires-Dist: numpy
Requires-Dist: scipy
Requires-Dist: sklearn
Requires-Dist: logging
Requires-Dist: logging-tree
Requires-Dist: pytest
Requires-Dist: six
